delibtools/__init__.py
delibtools/core.py
delibtools/utils.py
delibtools-0.1.6.dist-info/LICENSE
delibtools-0.1.6.dist-info/METADATA
delibtools-0.1.6.dist-info/WHEEL
delibtools-0.1.6.dist-info/top_level.txt
delibtools-0.1.6.dist-info/RECORD
